file2txt/__init__.py
file2txt/converter.py
file2txt/fanger.py
file2txt/image_processor.py
file2txt/parsers/__init__.py
file2txt/parsers/core.py
file2txt/parsers/csv_file_parser.py
file2txt/parsers/excel_file_parser.py
file2txt/parsers/html_file_parser.py
file2txt/parsers/image_file_parser.py
file2txt/parsers/markdown_file_parser.py
file2txt/parsers/marker_file_parser.py
file2txt-1.0.10.dist-info/METADATA
file2txt-1.0.10.dist-info/WHEEL
file2txt-1.0.10.dist-info/licenses/LICENSE
file2txt-1.0.10.dist-info/RECORD
