Metadata-Version: 2.4
Name: file2txt
Version: 1.0.10
Summary: file2txt is a Python library takes common file formats and turns them into plain text (a txt file) with Markdown styling.
Project-URL: Homepage, https://github.com/muchdogesec/file2txt
Project-URL: Issues, https://github.com/muchdogesec/file2txt/issues
Project-URL: dogesec HQ, https://dogesec.com
Author: dogesec
Maintainer: dogesec
License-File: LICENSE
Classifier: License :: OSI Approved :: Apache Software License
Classifier: Operating System :: OS Independent
Classifier: Programming Language :: Python :: 3
Requires-Python: >=3.9
Requires-Dist: bs4>=0.0.2
Requires-Dist: filetype>=1.2.0
Requires-Dist: google-cloud-vision>=3.4.5
Requires-Dist: grpcio-status>=1.62.2
Requires-Dist: lxml-html-clean>=0.1.1
Requires-Dist: markdownify>=0.14.1
Requires-Dist: mistune
Requires-Dist: pandas>=2.2.2
Requires-Dist: pillow>=10.0.1
Requires-Dist: python-dotenv>=1.0.1
Requires-Dist: readability-lxml>=0.8.1
Requires-Dist: requests>=2.32.4
Requires-Dist: tabulate>=0.9.0
Requires-Dist: xlrd
Provides-Extra: tests
Requires-Dist: pytest; extra == 'tests'
Requires-Dist: pytest-cov; extra == 'tests'
Requires-Dist: requests; extra == 'tests'
